{
  "devices": [
    {
      "model": "5",
      "images": {
        "path": "devices",
        "variations": [
          "Silver",
          "Space_Gray"
        ],
        "variations_colors": {
          "Silver": "#e4e4e2",
          "Space_Gray": "#262529"
        }
      },
      "parts": {
        "lcd": {
          "alternative": 7500,
          "medium": 11900
        },
        "battery": 9300,
        "camera": {
          "front": 4972,
          "rear": 4042
        },
        "port": 5336
      },
      "services": {
        "review": 3000,
        "clean": 3000
      }
    },
    {
      "model": "6",
      "images": {
        "path": "devices",
        "variations": [
          "Gold",
          "Silver",
          "Space_Gray"
        ],
        "variations_colors": {
          "Gold": "#e3ccb4",
          "Silver": "#e2e3e4",
          "Space_Gray": "#b1b2b7"
        }
      },
      "parts": {
        "lcd": {
          "alternative": 16500,
          "medium": 21300,
          "original": 25500
        },
        "battery": 11850,
        "earpiece": 3250,
        "camera": {
          "front": 4972,
          "rear": 6121
        },
        "lens": 3960,
        "port": 6987
      },
      "services": {
        "review": 3000,
        "clean": 3000
      }
    },
    {
      "model": "6 Plus",
      "images": {
        "path": "devices",
        "variations": [
          "Gold",
          "Silver",
          "Space_Gray"
        ],
        "variations_colors": {
          "Gold": "#e3ccb4",
          "Silver": "#e2e3e4",
          "Space_Gray": "#b1b2b7"
        }
      },
      "parts": {
        "lcd": {
          "alternative": 17900,
          "medium": 22700,
          "original": 29000
        },
        "battery": 13200,
        "earpiece": 3080,
        "camera": {
          "front": 5821,
          "rear": 9817
        },
        "lens": 3960,
        "port": 6987
      },
      "services": {
        "review": 3000,
        "clean": 3000
      }
    },
    {
      "model": "SE 2016",
      "images": {
        "path": "devices",
        "variations": [
          "Gold",
          "Rose_Gold",
          "Silver",
          "Space_Gray"
        ],
        "variations_colors": {
          "Gold": "#fadcc2",
          "Rose_Gold": "#ecc6c1",
          "Silver": "#e4e4e2",
          "Space_Gray": "#262529"
        }
      },
      "parts": {
        "lcd": {
          "alternative": 10700,
          "medium": 14500
        },
        "battery": 10100,
        "camera": {
          "front": 4972,
          "rear": 5313
        },
        "port": 5336
      },
      "services": {
        "review": 3000,
        "clean": 3000
      }
    },
    {
      "model": "6S",
      "images": {
        "path": "devices",
        "variations": [
          "Gold",
          "Rose_Gold",
          "Silver",
          "Space_Gray"
        ],
        "variations_colors": {
          "Gold": "#e3ccb4",
          "Rose_Gold": "#ecc6c1",
          "Silver": "#e2e3e4",
          "Space_Gray": "#b1b2b7"
        }
      },
      "parts": {
        "lcd": {
          "alternative": 17900,
          "medium": 22700,
          "original": 29000
        },
        "battery": 11850,
        "earpiece": 3250,
        "camera": {
          "front": 5336,
          "rear": 6583
        },
        "lens": 3960,
        "port": 6987
      },
      "services": {
        "review": 3000,
        "clean": 3000
      }
    },
    {
      "model": "6S Plus",
      "images": {
        "path": "devices",
        "variations": [
          "Gold",
          "Rose_Gold",
          "Silver",
          "Space_Gray"
        ],
        "variations_colors": {
          "Gold": "#e3ccb4",
          "Rose_Gold": "#ecc6c1",
          "Silver": "#e2e3e4",
          "Space_Gray": "#b1b2b7"
        }
      },
      "parts": {
        "lcd": {
          "alternative": 18300,
          "medium": 23800,
          "original": 30900
        },
        "battery": 13200,
        "earpiece": 3250,
        "camera": {
          "front": 7155,
          "rear": 10741
        },
        "lens": 3960,
        "port": 7495
      },
      "services": {
        "review": 3000,
        "clean": 3000
      }
    },
    {
      "model": "7",
      "images": {
        "path": "devices",
        "variations": [
          "Black",
          "Gold",
          "Rose_Gold",
          "Silver"
        ],
        "variations_colors": {
          "Black": "#2e3034",
          "Gold": "#e3ccb4",
          "Rose_Gold": "#ecc6c1",
          "Silver": "#e2e3e4"
        }
      },
      "parts": {
        "lcd": {
          "alternative": 20500,
          "medium": 26000,
          "original": 33800
        },
        "battery": 15600,
        "earpiece": 3850,
        "camera": {
          "front": 9580,
          "rear": 11434
        },
        "lens": 4950,
        "port": 9909
      },
      "services": {
        "review": 3000,
        "clean": 3000
      }
    },
    {
      "model": "7 Plus",
      "images": {
        "path": "devices",
        "variations": [
          "Black",
          "Gold",
          "Rose_Gold",
          "Silver"
        ],
        "variations_colors": {
          "Black": "#2e3034",
          "Gold": "#e3ccb4",
          "Rose_Gold": "#ecc6c1",
          "Silver": "#e2e3e4"
        }
      },
      "parts": {
        "lcd": {
          "alternative": 24000,
          "medium": 32000,
          "original": 41100
        },
        "battery": 16800,
        "earpiece": 5500,
        "camera": {
          "front": 12006,
          "rear": 31069
        },
        "lens": 5940,
        "port": 12069
      },
      "services": {
        "review": 3000,
        "clean": 3000
      }
    },
    {
      "model": "8",
      "images": {
        "path": "devices",
        "variations": [
          "Gold",
          "Silver",
          "Space_Gray"
        ],
        "variations_colors": {
          "Gold": "#f7e8dd",
          "Silver": "#e2e3e4",
          "Space_Gray": "#272729"
        }
      },
      "parts": {
        "lcd": {
          "alternative": 25000,
          "medium": 27700,
          "original": 37500
        },
        "battery": 16800,
        "glass": 17900,
        "case": 26400,
        "earpiece": 3850,
        "camera": {
          "front": 12006,
          "rear": 27500
        },
        "lens": 4950,
        "port": 12577
      },
      "services": {
        "review": 3000,
        "clean": 3000
      }
    },
    {
      "model": "8 Plus",
      "images": {
        "path": "devices",
        "variations": [
          "Gold",
          "Silver",
          "Space_Gray"
        ],
        "variations_colors": {
          "Gold": "#f7e8dd",
          "Silver": "#e2e3e4",
          "Space_Gray": "#272729"
        }
      },
      "parts": {
        "lcd": {
          "alternative": 26600,
          "medium": 34500,
          "original": 44100
        },
        "battery": 19950,
        "glass": 20500,
        "case": 28500,
        "earpiece": 5500,
        "camera": {
          "front": 15523,
          "rear": 34534
        },
        "lens": 5940,
        "port": 15118
      },
      "services": {
        "review": 3000,
        "clean": 3000
      }
    },
    {
      "model": "X",
      "images": {
        "path": "devices",
        "variations": [
          "Silver",
          "Space_Gray"
        ],
        "variations_colors": {
          "Silver": "#e4e4e2",
          "Space_Gray": "#262529"
        }
      },
      "parts": {
        "lcd": {
          "medium": 59300,
          "original": 83500
        },
        "battery": 24200,
        "glass": 24900,
        "case": 32900,
        "camera": {
          "front": 20010,
          "rear": 34072
        },
        "lens": 6600,
        "port": 18930
      },
      "services": {
        "review": 4000,
        "clean": 4000
      }
    },
    {
      "model": "XR",
      "images": {
        "path": "devices",
        "variations": [
          "Black",
          "Blue",
          "Coral",
          "Red",
          "White",
          "Yellow"
        ],
        "variations_colors": {
          "Black": "#2e3034",
          "Blue": "#48aee6",
          "Coral": "#ff6e5a",
          "Red": "#b41325",
          "White": "#f3f3f3",
          "Yellow": "#f9d045"
        }
      },
      "parts": {
        "lcd": {
          "medium": 50800,
          "original": 64100
        },
        "battery": 27700,
        "glass": 24900,
        "case": 32900,
        "camera": {
          "front": 19404,
          "rear": 31069
        },
        "lens": 5500,
        "port": 17659
      },
      "services": {
        "review": 4000,
        "clean": 4000
      }
    },
    {
      "model": "XS",
      "images": {
        "path": "devices",
        "variations": [
          "Gold",
          "Silver",
          "Space_Gray"
        ],
        "variations_colors": {
          "Gold": "#fadcc2",
          "Silver": "#e4e4e2",
          "Space_Gray": "#262529"
        }
      },
      "parts": {
        "lcd": {
          "medium": 59300,
          "original": 83500
        },
        "battery": 25190,
        "glass": 24900,
        "case": 32900,
        "camera": {
          "front": 20010,
          "rear": 38000
        },
        "lens": 6600,
        "port": 18930
      },
      "services": {
        "review": 4000,
        "clean": 4000
      }
    },
    {
      "model": "XS Max",
      "images": {
        "path": "devices",
        "variations": [
          "Gold",
          "Silver",
          "Space_Gray"
        ],
        "variations_colors": {
          "Gold": "#fadcc2",
          "Silver": "#e4e4e2",
          "Space_Gray": "#262529"
        }
      },
      "parts": {
        "lcd": {
          "medium": 70200,
          "original": 93400
        },
        "battery": 27700,
        "glass": 24900,
        "case": 34300,
        "camera": {
          "front": 22920,
          "rear": 38000
        },
        "lens": 6820,
        "port": 18930
      },
      "services": {
        "review": 4000,
        "clean": 4000
      }
    },
    {
      "model": "SE 2020",
      "images": {
        "path": "devices",
        "variations": [
          "Black",
          "Red",
          "White"
        ],
        "variations_colors": {
          "Black": "#262529",
          "Red": "#b41325",
          "White": "#f3f3f3"
        }
      },
      "parts": {
        "lcd": {
          "alternative": 25000,
          "medium": 27700,
          "original": 37500
        },
        "battery": 24050,
        "glass": 17900,
        "case": 26400,
        "camera": {
          "front": 12006,
          "rear": 27500
        },
        "lens": 4950,
        "port": 12577
      },
      "services": {
        "review": 3000,
        "clean": 3000
      }
    },
    {
      "model": "11",
      "images": {
        "path": "devices",
        "variations": [
          "Black",
          "Green",
          "Purple",
          "Red",
          "White",
          "Yellow"
        ],
        "variations_colors": {
          "Black": "#1f2020",
          "Green": "#aee1cd",
          "Purple": "#d1cdda",
          "Red": "#ba0c2e",
          "White": "#f9f6ef",
          "Yellow": "#ffe681"
        }
      },
      "parts": {
        "lcd": {
          "medium": 59300,
          "original": 77400
        },
        "battery": 33800,
        "glass": 33100,
        "case": 41700,
        "chip": 18000,
        "camera": {
          "front": 23648,
          "rear": 37999
        },
        "lens": 7150,
        "port": 24000
      },
      "services": {
        "review": 4000,
        "clean": 4000
      }
    },
    {
      "model": "11 Pro",
      "images": {
        "path": "devices",
        "variations": [
          "Gold",
          "Midnight_Green",
          "Silver",
          "Space_Gray"
        ],
        "variations_colors": {
          "Gold": "#fad7bd",
          "Midnight_Green": "#4e5851",
          "Silver": "#ebebe3",
          "Space_Gray": "#535150"
        }
      },
      "parts": {
        "lcd": {
          "medium": 65300,
          "original": 94400
        },
        "battery": 36200,
        "glass": 38700,
        "case": 51900,
        "chip": 20000,
        "camera": {
          "front": 24861,
          "rear": 50820
        },
        "lens": 8250,
        "port": 33000
      },
      "services": {
        "review": 4000,
        "clean": 4000
      }
    },
    {
      "model": "11 Pro Max",
      "images": {
        "path": "devices",
        "variations": [
          "Gold",
          "Midnight_Green",
          "Silver",
          "Space_Gray"
        ],
        "variations_colors": {
          "Gold": "#fad7bd",
          "Midnight_Green": "#4e5851",
          "Silver": "#ebebe3",
          "Space_Gray": "#535150"
        }
      },
      "parts": {
        "lcd": {
          "medium": 77800,
          "original": 118600
        },
        "battery": 36200,
        "glass": 42300,
        "case": 55300,
        "chip": 22000,
        "camera": {
          "front": 26074,
          "rear": 50820
        },
        "lens": 8250,
        "port": 35000
      },
      "services": {
        "review": 4000,
        "clean": 4000
      }
    },
    {
      "model": "12 Mini",
      "images": {
        "path": "devices",
        "variations": [
          "Black",
          "Blue",
          "Green",
          "Purple",
          "Red",
          "White"
        ],
        "variations_colors": {
          "Black": "#25212b",
          "Blue": "#023b63",
          "Green": "#d8efd5",
          "Purple": "#b7afe6",
          "Red": "#d82e2e",
          "White": "#f6f2ef"
        }
      },
      "parts": {
        "glass": 46000,
        "lens": 11550
      },
      "services": {
        "review": 5000,
        "clean": 5000
      }
    },
    {
      "model": "12",
      "images": {
        "path": "devices",
        "variations": [
          "Black",
          "Blue",
          "Green",
          "Purple",
          "Red",
          "White"
        ],
        "variations_colors": {
          "Black": "#25212b",
          "Blue": "#023b63",
          "Green": "#d8efd5",
          "Purple": "#b7afe6",
          "Red": "#d82e2e",
          "White": "#f6f2ef"
        }
      },
      "parts": {
        "lcd": {
          "medium": 230,
          "original": 400
        },
        "battery": 48300,
        "glass": 46000,
        "case": 61700,
        "chip": 25000,
        "camera": {
          "front": 34563,
          "rear": 51975
        },
        "lens": 11550,
        "port": 45000
      },
      "services": {
        "review": 5000,
        "clean": 5000
      }
    },
    {
      "model": "12 Pro",
      "images": {
        "path": "devices",
        "variations": [
          "Gold",
          "Graphite",
          "Pacific_Blue",
          "Silver"
        ],
        "variations_colors": {
          "Gold": "#fcebd3",
          "Graphite": "#52514d",
          "Pacific_Blue": "#2d4e5c",
          "Silver": "#e3e4df"
        }
      },
      "parts": {
        "lcd": {
          "medium": 230,
          "original": 400
        },
        "battery": 48300,
        "glass": 50800,
        "case": 66500,
        "chip": 25000,
        "camera": {
          "front": 42446,
          "rear": 68145
        },
        "lens": 11550,
        "port": 45000
      },
      "services": {
        "review": 5000,
        "clean": 5000
      }
    },
    {
      "model": "12 Pro Max",
      "images": {
        "path": "devices",
        "variations": [
          "Gold",
          "Graphite",
          "Pacific_Blue",
          "Silver"
        ],
        "variations_colors": {
          "Gold": "#fcebd3",
          "Graphite": "#52514d",
          "Pacific_Blue": "#2d4e5c",
          "Silver": "#e3e4df"
        }
      },
      "parts": {
        "lcd": {
          "medium": 280,
          "original": 590
        },
        "battery": 54500,
        "glass": 54400,
        "case": 72100,
        "camera": {
          "front": 42446,
          "rear": 68145
        },
        "lens": 11550,
        "port": 45000
      },
      "services": {
        "review": 5000,
        "clean": 5000
      }
    },
    {
      "model": "13 Mini",
      "images": {
        "path": "devices",
        "variations": [
          "Blue",
          "Green",
          "Midnight",
          "Pink",
          "Red",
          "Starlight"
        ],
        "variations_colors": {
          "Blue": "#276787",
          "Green": "#394c38",
          "Midnight": "#232a31",
          "Pink": "#faddd7",
          "Red": "#bf0013",
          "Starlight": "#faf6f2"
        }
      },
      "parts": {
        "lens": 14850
      },
      "services": {
        "review": 6000,
        "clean": 6000
      }
    },
    {
      "model": "13",
      "images": {
        "path": "devices",
        "variations": [
          "Blue",
          "Green",
          "Midnight",
          "Pink",
          "Red",
          "Starlight"
        ],
        "variations_colors": {
          "Blue": "#276787",
          "Green": "#394c38",
          "Midnight": "#232a31",
          "Pink": "#faddd7",
          "Red": "#bf0013",
          "Starlight": "#faf6f2"
        }
      },
      "parts": {
        "lcd": {
          "original": 500
        },
        "battery": 54500,
        "glass": 54400,
        "camera": {
          "rear": 51975
        },
        "lens": 14850,
        "port": 40000
      },
      "services": {
        "review": 6000,
        "clean": 6000
      }
    },
    {
      "model": "13 Pro",
      "images": {
        "path": "devices",
        "variations": [
          "Alpine_Green",
          "Gold",
          "Graphite",
          "Sierra_Blue",
          "Silver"
        ],
        "variations_colors": {
          "Alpine_Green": "#576856",
          "Gold": "#fae7cf",
          "Graphite": "#54524f",
          "Sierra_Blue": "#a7c1d9",
          "Silver": "#f1f2ed"
        }
      },
      "parts": {
        "battery": 62900,
        "glass": 59300,
        "lens": 22000,
        "port": 50000
      },
      "services": {
        "review": 6000,
        "clean": 6000
      }
    },
    {
      "model": "13 Pro Max",
      "images": {
        "path": "devices",
        "variations": [
          "Alpine_Green",
          "Gold",
          "Graphite",
          "Sierra_Blue",
          "Silver"
        ],
        "variations_colors": {
          "Alpine_Green": "#576856",
          "Gold": "#fae7cf",
          "Graphite": "#54524f",
          "Sierra_Blue": "#a7c1d9",
          "Silver": "#f1f2ed"
        }
      },
      "parts": {
        "battery": 71400,
        "glass": 67800,
        "lens": 22000,
        "port": 55000
      },
      "services": {
        "review": 6000,
        "clean": 6000
      }
    },
    {
      "model": "SE 2022",
      "images": {
        "path": "devices",
        "variations": [
          "Midnight",
          "Red",
          "Starlight"
        ],
        "variations_colors": {
          "Midnight": "#232a31",
          "Red": "#bf0013",
          "Starlight": "#faf6f2"
        }
      },
      "parts": {
        "lens": 4950
      }
    },
    {
      "model": "14",
      "images": {
        "path": "devices",
        "variations": [
          "Blue",
          "Midnight",
          "Purple",
          "Red",
          "Starlight",
          "Yellow"
        ],
        "variations_colors": {
          "Blue": "#a0b4c7",
          "Midnight": "#222930",
          "Purple": "#e6ddeb",
          "Red": "#fc0324",
          "Starlight": "#faf6f2",
          "Yellow": "#f9e479"
        }
      },
      "parts": {
        "lens": 27500
      }
    },
    {
      "model": "14 Plus",
      "images": {
        "path": "devices",
        "variations": [
          "Blue",
          "Midnight",
          "Purple",
          "Red",
          "Starlight",
          "Yellow"
        ],
        "variations_colors": {
          "Blue": "#a0b4c7",
          "Midnight": "#222930",
          "Purple": "#e6ddeb",
          "Red": "#fc0324",
          "Starlight": "#faf6f2",
          "Yellow": "#f9e479"
        }
      },
      "parts": {
        "lens": 27500
      }
    },
    {
      "model": "14 Pro",
      "images": {
        "path": "devices",
        "variations": [
          "Deep_Purple",
          "Gold",
          "Silver",
          "Space_Black"
        ],
        "variations_colors": {
          "Deep_Purple": "#594f63",
          "Gold": "#f4e8ce",
          "Silver": "#f0f2f2",
          "Space_Black": "#403e3d"
        }
      },
      "parts": {
        "lens": 29700
      }
    },
    {
      "model": "14 Pro Max",
      "images": {
        "path": "devices",
        "variations": [
          "Deep_Purple",
          "Gold",
          "Silver",
          "Space_Black"
        ],
        "variations_colors": {
          "Deep_Purple": "#594f63",
          "Gold": "#f4e8ce",
          "Silver": "#f0f2f2",
          "Space_Black": "#403e3d"
        }
      },
      "parts": {
        "lens": 29700
      }
    }
  ],
  "messages": {
    "screen": "Las pantallas originales poseen un chip el cuál se encuentra cifrado con información única de tu iPhone. Al cambiar la pantalla se puede intentar realizar el traspaso del mismo a la nueva pantalla mediante un proceso de microsoldadura y una máquina especial para este trabajo. El mismo tiene un precio de price. Si el procedimiento no es efectivo no se cobra el monto de price.",
    "battery": "Al cambiar la bateria de estos modelos por una nueva el equipo deja de marcar condición. En este momento contamos con una maquina especial la cual nos permite configurar el 100% de la bateria nueva al cambiarla. Siempre hay una minima chance de que quede sin condición de bateria pero normalmente no sucede."
  }
}